api_validator/Test_local.py
api_validator/__init__.py
api_validator/core.cp38-win_amd64.pyd
api_validator/core.cpp
api_validator/core.pyx
api_validator/core_py.py
api_validator/fields.py
api_validator/license_validator.py
api_validator/models.py
api_validator/validator.py
api_validator_sdk-1.0.0.dist-info/METADATA
api_validator_sdk-1.0.0.dist-info/WHEEL
api_validator_sdk-1.0.0.dist-info/entry_points.txt
api_validator_sdk-1.0.0.dist-info/top_level.txt
api_validator_sdk-1.0.0.dist-info/RECORD
